china_stock_data/__init__.py
china_stock_data/__version__.py
china_stock_data/config.py
china_stock_data/fetchers/README.md
china_stock_data/fetchers/__init__.py
china_stock_data/fetchers/base_fetcher.py
china_stock_data/fetchers/fundamentals/__init__.py
china_stock_data/fetchers/fundamentals/dividend_fetcher.py
china_stock_data/fetchers/fundamentals/earnings_fetcher.py
china_stock_data/fetchers/fundamentals/financial_statements_fetcher.py
china_stock_data/fetchers/fundamentals/repurchase_fetcher.py
china_stock_data/fetchers/fundamentals/restricted_release_fetcher.py
china_stock_data/fetchers/fundamentals/top_shareholders_fetcher.py
china_stock_data/fetchers/index/__init__.py
china_stock_data/fetchers/index/components_fetcher.py
china_stock_data/fetchers/index/list_fetcher.py
china_stock_data/fetchers/index/us_fetcher.py
china_stock_data/fetchers/market/__init__.py
china_stock_data/fetchers/market/lhb_fetcher.py
china_stock_data/fetchers/market/margin_financing_fetcher.py
china_stock_data/fetchers/market/northbound_holdings_fetcher.py
china_stock_data/fetchers/market/sse_deal_daily_fetcher.py
china_stock_data/fetchers/market/sse_summary_fetcher.py
china_stock_data/fetchers/market/szse_area_summary_fetcher.py
china_stock_data/fetchers/market/szse_sector_summary_fetcher.py
china_stock_data/fetchers/market/szse_summary_fetcher.py
china_stock_data/fetchers/stock/__init__.py
china_stock_data/fetchers/stock/chip_fetcher.py
china_stock_data/fetchers/stock/fund_flow_fetcher.py
china_stock_data/fetchers/stock/hist_fetcher.py
china_stock_data/fetchers/stock/info_fetcher.py
china_stock_data/fetchers/stock/realtime_fetcher.py
china_stock_data/index_data.py
china_stock_data/market_data.py
china_stock_data/persistent_dict.py
china_stock_data/stock_data.py
china_stock_data/trading_time_checker.py
china_stock_data/utils.py
china_stock_data-0.2.2.dist-info/METADATA
china_stock_data-0.2.2.dist-info/WHEEL
china_stock_data-0.2.2.dist-info/entry_points.txt
china_stock_data-0.2.2.dist-info/RECORD
