Metadata-Version: 2.4
Name: china_stock_data
Version: 0.2.2
Summary: 
Author: sunjuzhong
Author-email: 129019668+sunjuzhong@users.noreply.github.com
Requires-Python: >=3.10,<4.0
Classifier: Programming Language :: Python :: 3
Classifier: Programming Language :: Python :: 3.10
Classifier: Programming Language :: Python :: 3.11
Classifier: Programming Language :: Python :: 3.12
Classifier: Programming Language :: Python :: 3.13
Classifier: Programming Language :: Python :: 3.14
Requires-Dist: akshare (>=1.17.0,<2.0.0)
Requires-Dist: pandas (>=2.2.3,<3.0.0)
